batch_processing/__init__.py
batch_processing/batch.py
batch_processing-1.0.1.dist-info/LICENSE
batch_processing-1.0.1.dist-info/METADATA
batch_processing-1.0.1.dist-info/WHEEL
batch_processing-1.0.1.dist-info/top_level.txt
batch_processing-1.0.1.dist-info/RECORD
