Metadata-Version: 2.1
Name: batch-processing
Version: 1.0.1
Summary: A Python library to make batchable Python scripts.
Home-page: https://github.com/emmcb/batch-processing
Author: Emmanuel Chaboud
Classifier: License :: OSI Approved :: Apache Software License
Classifier: Programming Language :: Python :: 3
Classifier: Programming Language :: Python :: 3 :: Only
Classifier: Operating System :: OS Independent
Classifier: Topic :: Software Development :: Libraries :: Python Modules
Requires-Python: >=3
License-File: LICENSE
Requires-Dist: mergedeep
Requires-Dist: tqdm
Requires-Dist: unified-path
